helloworld.py
helloworld_dylanballback-0.0.1.dist-info/METADATA
helloworld_dylanballback-0.0.1.dist-info/WHEEL
helloworld_dylanballback-0.0.1.dist-info/license.txt
helloworld_dylanballback-0.0.1.dist-info/top_level.txt
helloworld_dylanballback-0.0.1.dist-info/RECORD
