Metadata-Version: 2.1
Name: helloworld-dylanballback
Version: 0.0.1
Summary: Say, hello!
Home-page: https://github.com/dylanballback/packagetest
Author: Dylan Ballback
Author-email: Dylanballback19@gmail.com
License: UNKNOWN
Platform: UNKNOWN
